yaql/__init__.py
yaql/legacy.py
yaql/yaql_interface.py
yaql/yaqlization.py
yaql/_ply/__init__.py
yaql/_ply/lex.py
yaql/_ply/yacc.py
yaql/cli/__init__.py
yaql/cli/cli_functions.py
yaql/cli/run.py
yaql/contrib/README.rst
yaql/language/__init__.py
yaql/language/contexts.py
yaql/language/conventions.py
yaql/language/exceptions.py
yaql/language/expressions.py
yaql/language/factory.py
yaql/language/lexer.py
yaql/language/parser.out
yaql/language/parser.py
yaql/language/runner.py
yaql/language/specs.py
yaql/language/utils.py
yaql/language/yaqltypes.py
yaql/standard_library/__init__.py
yaql/standard_library/boolean.py
yaql/standard_library/branching.py
yaql/standard_library/collections.py
yaql/standard_library/common.py
yaql/standard_library/date_time.py
yaql/standard_library/legacy.py
yaql/standard_library/math.py
yaql/standard_library/queries.py
yaql/standard_library/regex.py
yaql/standard_library/strings.py
yaql/standard_library/system.py
yaql/standard_library/yaqlized.py
yaql/tests/__init__.py
yaql/tests/test_boolean.py
yaql/tests/test_branching.py
yaql/tests/test_collections.py
yaql/tests/test_common.py
yaql/tests/test_contexts.py
yaql/tests/test_datetime.py
yaql/tests/test_engine.py
yaql/tests/test_legacy.py
yaql/tests/test_math.py
yaql/tests/test_miscellaneous.py
yaql/tests/test_queries.py
yaql/tests/test_regex.py
yaql/tests/test_resolution.py
yaql/tests/test_strings.py
yaql/tests/test_system.py
yaql/tests/test_type_aggregation.py
yaql/tests/test_yaql_interface.py
yaql/tests/test_yaqlization.py
yaql-3.2.0.dist-info/AUTHORS
yaql-3.2.0.dist-info/LICENSE
yaql-3.2.0.dist-info/METADATA
yaql-3.2.0.dist-info/WHEEL
yaql-3.2.0.dist-info/entry_points.txt
yaql-3.2.0.dist-info/pbr.json
yaql-3.2.0.dist-info/top_level.txt
yaql-3.2.0.dist-info/RECORD
